KratosMultiphysics/ChimeraApplication/__init__.py
KratosMultiphysics/ChimeraApplication/__init__.pyi
KratosMultiphysics/ChimeraApplication/chimera_modelpart_import.py
KratosMultiphysics/ChimeraApplication/chimera_setup_utils.py
KratosMultiphysics/ChimeraApplication/fluid_chimera_analysis.py
KratosMultiphysics/ChimeraApplication/navier_stokes_solver_fractionalstep_chimera.py
KratosMultiphysics/ChimeraApplication/navier_stokes_solver_vmsmonolithic_chimera.py
KratosMultiphysics/ChimeraApplication/python_solvers_wrapper_fluid_chimera.py
KratosMultiphysics/ChimeraApplication/rotate_region_process.py
KratosMultiphysics/.libs/KratosChimeraApplication.cpython-39-x86_64-linux-gnu.so
kratoschimeraapplication-10.4.0.dist-info/METADATA
kratoschimeraapplication-10.4.0.dist-info/WHEEL
kratoschimeraapplication-10.4.0.dist-info/RECORD
